{
    "Food waste": 0,
    "Toilet tube": 1,
    "Egg carton": 2,
    "Drink carton": 3,
    "Corrugated carton": 4,
    "Meal carton": 5,
    "Pizza box": 6,
    "Paper cup": 7,
    "Normal paper": 8,
    "Paper bag": 9,
    "Plastified paper bag": 10,
    "Wrapping paper": 11,
    "Tissues": 12,
    "Magazine paper": 13,
    "Rope & strings": 14,
    "Aluminium foil": 15,
    "Battery": 16,
    "Aluminium blister pack": 17,
    "Carded blister pack": 18,
    "Other plastic bottle": 19,
    "Clear plastic bottle": 20,
    "Glass bottle": 21,
    "Plastic bottle cap": 22,
    "Metal bottle cap": 23,
    "Broken glass": 24,
    "Food Can": 25,
    "Aerosol": 26,
    "Drink can": 27,
    "Disposable plastic cup": 28,
    "Foam cup": 29,
    "Glass cup": 30,
    "Other plastic cup": 31,
    "Plastic lid": 32,
    "Metal lid": 33,
    "Other plastic": 34,
    "Plastic film": 35,
    "Six pack rings": 36,
    "Garbage bag": 37,
    "Other plastic wrapper": 38,
    "Single-use carrier bag": 39,
    "Polypropylene bag": 40,
    "Crisp packet": 41,
    "Spread tub": 42,
    "Tupperware": 43,
    "Disposable food container": 44,
    "Foam food container": 45,
    "Other plastic container": 46,
    "Plastic glooves": 47,
    "Plastic utensils": 48,
    "Pop tab": 49,
    "Scrap metal": 50,
    "Shoe": 51,
    "Squeezable tube": 52,
    "Plastic straw": 53,
    "Paper straw": 54,
    "Styrofoam piece": 55,
    "Unlabeled litter": 56,
    "Cigarette": 57
}